randomstringpackage/__about__.py
randomstringpackage/__init__.py
randomstringpackage-0.0.0.dev0.dist-info/licenses/LICENSE.txt
randomstringpackage-0.0.0.dev0.dist-info/WHEEL
randomstringpackage-0.0.0.dev0.dist-info/METADATA
randomstringpackage-0.0.0.dev0.dist-info/RECORD
