Metadata-Version: 2.4
Name: randomstringpackage
Version: 0.0.0.dev0
Summary: 
Keywords: 
Author-email: "U.N. Owen" <void@some.where>
Requires-Python: >=3.8
License-Expression: MIT
Classifier: Development Status :: 4 - Beta
Classifier: Programming Language :: Python
Classifier: Programming Language :: Python :: 3.8
Classifier: Programming Language :: Python :: 3.9
Classifier: Programming Language :: Python :: 3.10
Classifier: Programming Language :: Python :: 3.11
Classifier: Programming Language :: Python :: 3.12
Classifier: Programming Language :: Python :: Implementation :: CPython
Classifier: Programming Language :: Python :: Implementation :: PyPy
License-File: LICENSE.txt
Project-URL: Documentation, https://github.com/U.N. Owen/randomstringpackage#readme
Project-URL: Issues, https://github.com/U.N. Owen/randomstringpackage/issues
Project-URL: Source, https://github.com/U.N. Owen/randomstringpackage
